jupyterlab_proxy_gui/__init__.py
jupyterlab_proxy_gui/_version.py
jupyterlab_proxy_gui/handlers.py
jupyterlab_proxy_gui/labextension/jupyterlab-proxy-gui-0.1.16.tgz
jupyterlab_proxy_gui-0.1.16.data/data/etc/jupyter/jupyter_notebook_config.d/jupyterlab_proxy_gui.json
jupyterlab_proxy_gui-0.1.16.data/data/share/jupyter/lab/extensions/jupyterlab-proxy-gui-0.1.16.tgz
jupyterlab_proxy_gui-0.1.16.dist-info/LICENSE
jupyterlab_proxy_gui-0.1.16.dist-info/METADATA
jupyterlab_proxy_gui-0.1.16.dist-info/WHEEL
jupyterlab_proxy_gui-0.1.16.dist-info/top_level.txt
jupyterlab_proxy_gui-0.1.16.dist-info/RECORD
