Metadata-Version: 2.1
Name: jupyterlab-proxy-gui
Version: 0.1.16
Summary: A JupyterLab extension to control the configurable-http-proxy of JupyterHub.
Home-page: https://github.com/VK/jupyterlab-proxy-gui
Author: Viktor Krueckl
License: BSD-3-Clause
Keywords: Jupyter,JupyterLab
Platform: Linux
Platform: Mac OS X
Platform: Windows
Classifier: License :: OSI Approved :: BSD License
Classifier: Programming Language :: Python
Classifier: Programming Language :: Python :: 3
Classifier: Programming Language :: Python :: 3.5
Classifier: Programming Language :: Python :: 3.6
Classifier: Programming Language :: Python :: 3.7
Classifier: Programming Language :: Python :: 3.8
Classifier: Framework :: Jupyter
License-File: LICENSE
Requires-Dist: jupyterlab (>=3.0)
